crosstalk_correction
