Metadata-Version: 1.1
Name: crosstalk-correction
Version: 1.0.3
Summary: Python 3 implementation of maximum impact estimation (Donato et al., 2013)
Home-page: https://github.com/kathyxchen/crosstalk-correction
Author: Kathy Chen
Author-email: chen.kathleenm@gmail.com
License: LICENSE
Platform: UNKNOWN
Classifier: Intended Audience :: Developers
Classifier: License :: OSI Approved :: BSD License
Classifier: Operating System :: OS Independent
Classifier: Programming Language :: Python
Classifier: Programming Language :: Python :: 3
Classifier: Topic :: Scientific/Engineering :: Bio-Informatics
